ani_title/__init__.py
ani_title-0.1.1.dist-info/licenses/LICENSE
ani_title-0.1.1.dist-info/METADATA
ani_title-0.1.1.dist-info/WHEEL
ani_title-0.1.1.dist-info/top_level.txt
ani_title-0.1.1.dist-info/RECORD
