Metadata-Version: 2.4
Name: ani-title
Version: 0.1.1
Summary: Get official anime titles from Kitsu API by name
Home-page: https://github.com/wxxoxo/ani-title
Author: Arise
Author-email: AriseAgatsuma@gmail.com
Classifier: Programming Language :: Python :: 3
Classifier: Operating System :: OS Independent
Classifier: License :: OSI Approved :: MIT License
Classifier: Topic :: Utilities
Requires-Python: >=3.6
License-File: LICENSE
Requires-Dist: requests
Dynamic: author
Dynamic: author-email
Dynamic: classifier
Dynamic: description
Dynamic: description-content-type
Dynamic: home-page
Dynamic: license-file
Dynamic: requires-dist
Dynamic: requires-python
Dynamic: summary
